DriverPAC3120/__init__.py
DriverPAC3120/funciones.py
DriverPAC3120-1.2.2.dist-info/METADATA
DriverPAC3120-1.2.2.dist-info/WHEEL
DriverPAC3120-1.2.2.dist-info/top_level.txt
DriverPAC3120-1.2.2.dist-info/RECORD
