Metadata-Version: 2.1
Name: DriverPAC3120
Version: 1.2.2
Summary: Driver PAC3120
Home-page: 
Author: Cristian Arias
Author-email: c.arias4p@gmail.com
License: MIT
Requires-Dist: pymupdf
